setup.cfg
setup.py
jut/__init__.py
jut/cli.py
jut/common.py
jut/config.py
jut/defaults.py
jut/formatters.py
jut/api/__init__.py
jut/api/accounts.py
jut/api/auth.py
jut/api/authorizations.py
jut/api/data_engine.py
jut/api/deployments.py
jut/api/environment.py
jut/api/integrations.py
jut/api/programs.py
jut/commands/__init__.py
jut/commands/configs.py
jut/commands/jobs.py
jut/commands/programs.py
jut/commands/run.py
jut/commands/upload.py
jut/exceptions/__init__.py
jut/util/__init__.py
jut/util/console.py
jut/util/dates.py
jut_tools.egg-info/PKG-INFO
jut_tools.egg-info/SOURCES.txt
jut_tools.egg-info/dependency_links.txt
jut_tools.egg-info/entry_points.txt
jut_tools.egg-info/not-zip-safe
jut_tools.egg-info/pbr.json
jut_tools.egg-info/requires.txt
jut_tools.egg-info/top_level.txt