Metadata-Version: 1.1
Name: jut-tools
Version: 0.8
Summary: jut command line tools
Home-page: https://github.com/jut-io/jut-python-tools
Author: Rodney Gomes
Author-email: rodney@jut.io
License: MIT License
Download-URL: https://github.com/jut-io/jut-python-tools/tarball/0.8
Platform: UNKNOWN
